lightbulb/ext/hecate/__init__.py
lightbulb/ext/hecate/__main__.py
lightbulb/ext/hecate/errors.py
lightbulb/ext/hecate/params.py
lightbulb/ext/hecate/plugin.py
lightbulb/ext/hecate/properties.py
lightbulb/ext/hecate/template/__modify__.py
lightbulb/ext/hecate/template/events/GuildMessageCreateEvent.py
lightbulb/ext/hecate/template/events/_GuildMessageDeleteEvent.py
lightbulb/ext/hecate/template/slash-commands/ping.py
lightbulb/ext/hecate/template/slash-commands/pong_count.py
lightbulb_ext_hecate-0.1.6.dist-info/LICENSE
lightbulb_ext_hecate-0.1.6.dist-info/METADATA
lightbulb_ext_hecate-0.1.6.dist-info/WHEEL
lightbulb_ext_hecate-0.1.6.dist-info/RECORD
