Metadata-Version: 2.1
Name: lightbulb-ext-hecate
Version: 0.1.6
Summary: File driven wrappers around lightbulb extensions and plugins.
Home-page: https://github.com/radkii/lightbulb-ext-hecate
License: MIT
Author: Radkii
Author-email: real.radkii@gmail.com
Requires-Python: >=3.9,<3.12
Classifier: License :: OSI Approved :: MIT License
Classifier: Programming Language :: Python :: 3
Classifier: Programming Language :: Python :: 3.9
Classifier: Programming Language :: Python :: 3.10
Classifier: Programming Language :: Python :: 3.11
Requires-Dist: hikari-lightbulb (>=2.3.1,<3.0.0)
Project-URL: Repository, https://github.com/radkii/lightbulb-ext-hecate
